ftts/__init__.py
ftts/__main__.py
ftts/logger.py
ftts/utils.py
ftts/audio/__init__.py
ftts/audio/base_model.py
ftts/audio/batch_processor.py
ftts/audio/utils.py
ftts/audio/detokenizer/__init__.py
ftts/audio/detokenizer/snac_detokenizer.py
ftts/audio/detokenizer/spark_detokenizer.py
ftts/audio/tokenizer/__init__.py
ftts/audio/tokenizer/mega_tokenizer.py
ftts/audio/tokenizer/spark_tokenizer.py
ftts/commands/__init__.py
ftts/commands/infer.py
ftts/commands/serve.py
ftts/commands/utils.py
ftts/engine/__init__.py
ftts/engine/auto_engine.py
ftts/engine/base_engine.py
ftts/engine/mega_engine.py
ftts/engine/orpheus_engine.py
ftts/engine/spark_engine.py
ftts/engine/utils.py
ftts/llm/__init__.py
ftts/llm/base_llm.py
ftts/llm/init_llm.py
ftts/llm/llama_cpp_generator.py
ftts/llm/mlx_lm_generator.py
ftts/llm/sglang_generator.py
ftts/llm/torch_generator.py
ftts/llm/trtllm_generator.py
ftts/llm/vllm_generator.py
ftts/modules/__init__.py
ftts/modules/blocks/__init__.py
ftts/modules/blocks/layers.py
ftts/modules/blocks/samper.py
ftts/modules/blocks/vocos.py
ftts/modules/encoder_decoder/__init__.py
ftts/modules/encoder_decoder/feat_decoder.py
ftts/modules/encoder_decoder/feat_encoder.py
ftts/modules/encoder_decoder/wave_generator.py
ftts/modules/fsq/__init__.py
ftts/modules/fsq/finite_scalar_quantization.py
ftts/modules/fsq/residual_fsq.py
ftts/modules/mega_modules/__init__.py
ftts/modules/mega_modules/ph_tone_convert.py
ftts/modules/mega_modules/text_encoder.py
ftts/modules/mega_modules/utils.py
ftts/modules/mega_modules/whisper_small.py
ftts/modules/mega_modules/ar_dur/__init__.py
ftts/modules/mega_modules/ar_dur/ar_dur_predictor.py
ftts/modules/mega_modules/ar_dur/layers.py
ftts/modules/mega_modules/ar_dur/ling_dict.py
ftts/modules/mega_modules/ar_dur/rel_transformer.py
ftts/modules/mega_modules/ar_dur/rot_transformer.py
ftts/modules/mega_modules/ar_dur/seq_utils.py
ftts/modules/mega_modules/ar_dur/transformer.py
ftts/modules/mega_modules/llm_dit/__init__.py
ftts-0.3.0.dist-info/METADATA
ftts-0.3.0.dist-info/WHEEL
ftts-0.3.0.dist-info/entry_points.txt
ftts-0.3.0.dist-info/RECORD
