Metadata-Version: 2.4
Name: ftts
Version: 0.3.0
Summary: fast tts inference engine
Author-email: 王梦迪 <wangmengdi06@58.com>
Requires-Python: >=3.10
Requires-Dist: av>=15.0.0
Requires-Dist: einx>=0.3.0
Requires-Dist: fastapi[standard]>=0.115.14
Requires-Dist: jsonargparse[signatures]>=4.40.0
Requires-Dist: numpy>=2.2.6
Requires-Dist: omegaconf>=2.3.0
Requires-Dist: osc-data>=0.1.9
Requires-Dist: safetensors>=0.5.3
Requires-Dist: snac>=1.2.1
Requires-Dist: soundfile>=0.13.1
Requires-Dist: soxr>=0.5.0.post1
Requires-Dist: torch>=2.7.1
Requires-Dist: torchaudio>=2.7.1
Requires-Dist: transformers>=4.53.0
Provides-Extra: llama-cpp
Requires-Dist: llama-cpp-python>=0.3.13; extra == 'llama-cpp'
